{
  "url": "https://guardians4kenyankids.org",
  "email": "onb.rjs+guardians4kenyankidsorg@gmail.com",
  "domain": "guardians4kenyankids.org",
  "startedAt": "2026-05-18T02:29:32.097Z",
  "steps": [
    {
      "name": "no-form",
      "ts": "2026-05-18T02:30:00.193Z",
      "url": "https://guardians4kenyankids.org/contact-us",
      "noFormReason": "no_email_form"
    }
  ],
  "finishedAt": "2026-05-18T02:30:00.193Z",
  "outcome": {
    "status": "no_form",
    "noFormReason": "no_email_form"
  }
}