{
  "url": "https://caroldasneves.com",
  "email": "onb.rjs+caroldasnevescom@gmail.com",
  "domain": "caroldasneves.com",
  "startedAt": "2026-05-17T23:24:22.887Z",
  "steps": [
    {
      "name": "form-inspected",
      "ts": "2026-05-17T23:24:35.009Z",
      "fields": [
        "First Name",
        "Last Name",
        "Email Address"
      ],
      "cta": "Sign Up",
      "placement": "Popup / Modal",
      "formType": "Marketing Lead Capture"
    },
    {
      "name": "pre-submit-captured",
      "ts": "2026-05-17T23:24:35.112Z",
      "url": "https://www.caroldasneves.com/"
    },
    {
      "name": "confirmation-detected",
      "ts": "2026-05-17T23:24:42.145Z",
      "state": "inline",
      "evidence": "Thank you!",
      "url": "https://www.caroldasneves.com/"
    }
  ],
  "finishedAt": "2026-05-17T23:24:42.145Z",
  "outcome": {
    "status": "submitted",
    "confirmationState": "inline"
  }
}