{
  "url": "https://coastalconnectionsca.com",
  "email": "onb.rjs+coastalconnectionscacom@gmail.com",
  "domain": "coastalconnectionsca.com",
  "startedAt": "2026-05-18T02:56:27.166Z",
  "steps": [
    {
      "name": "form-inspected",
      "ts": "2026-05-18T02:56:43.226Z",
      "fields": [
        "First Name(required)",
        "Last Name(required)",
        "Email(required)",
        "text",
        "First Name",
        "Last Name",
        "Participant Age",
        "Area of Interest",
        "What does your young adult enjoy doing out in the community?",
        "What are your son/daughter interests and hobbies?",
        "Is there anything they strongly dislike?",
        "What are your main goals for your young adult?",
        "Making friends",
        "Community Integration",
        "Wellness Wednesdays (Staying active)",
        "Independence",
        "Job Skills",
        "Other",
        "If you selected other, please specify",
        "Are there any behaviors or triggers we should know about?",
        "What strategies help your son/daughter to succeed?",
        "Level of independence?",
        "Is your son/daughter able to safely participate in community outings?",
        "Any allergies or medical concerns we should know about?",
        "How will services be funded?",
        "If SDP, What is the name of your FMS (Financial Management Service)",
        "First Name",
        "Last Name",
        "text",
        "What is your son/daughter's UCI #",
        "message-yui_43cca85a-f14d-4ed5-9bce-b25faa81a812-field"
      ],
      "cta": "SubmitSubmit",
      "placement": "Popup / Modal",
      "formType": "Support"
    },
    {
      "name": "pre-submit-captured",
      "ts": "2026-05-18T02:56:43.383Z",
      "url": "https://www.coastalconnectionsca.com/get-started"
    },
    {
      "name": "confirmation-detected",
      "ts": "2026-05-18T02:56:56.588Z",
      "state": "no-confirmation",
      "evidence": "",
      "url": "https://www.coastalconnectionsca.com/get-started"
    }
  ],
  "finishedAt": "2026-05-18T02:56:56.588Z",
  "outcome": {
    "status": "submitted",
    "confirmationState": "no-confirmation"
  }
}