{
  "url": "https://iontasmagazine.com",
  "email": "onb.rjs+iontasmagazinecom@gmail.com",
  "domain": "iontasmagazine.com",
  "startedAt": "2026-05-18T03:43:28.007Z",
  "steps": [
    {
      "name": "form-inspected",
      "ts": "2026-05-18T03:43:40.602Z",
      "fields": [
        "Email Address"
      ],
      "cta": "Subscribe",
      "placement": "Popup / Modal",
      "formType": "Marketing Lead Capture"
    },
    {
      "name": "pre-submit-captured",
      "ts": "2026-05-18T03:43:40.821Z",
      "url": "https://www.iontasmagazine.com/"
    },
    {
      "name": "confirmation-detected",
      "ts": "2026-05-18T03:43:47.860Z",
      "state": "inline",
      "evidence": "GRMA (Thank you) <3",
      "url": "https://www.iontasmagazine.com/"
    }
  ],
  "finishedAt": "2026-05-18T03:43:47.860Z",
  "outcome": {
    "status": "submitted",
    "confirmationState": "inline"
  }
}